DCM/__init__.py
DCM/main.py
DCM2/__init__.py
DCM2/main.py
DCM2-0.2.dist-info/LICENSE.txt
DCM2-0.2.dist-info/METADATA
DCM2-0.2.dist-info/WHEEL
DCM2-0.2.dist-info/top_level.txt
DCM2-0.2.dist-info/RECORD
